LICENSE.txt
MANIFEST.in
README.rst
release-history.rst
requirements.txt
setup.py
pandas_mate/__init__.py
pandas_mate/csv_io.py
pandas_mate/sql_io.py
pandas_mate/transform.py
pandas_mate/util.py
pandas_mate/zzz_manual_install.py
pandas_mate.egg-info/PKG-INFO
pandas_mate.egg-info/SOURCES.txt
pandas_mate.egg-info/dependency_links.txt
pandas_mate.egg-info/top_level.txt
pandas_mate/__pycache__/__init__.cpython-34.pyc
pandas_mate/pkg/__init__.py
pandas_mate/pkg/prettytable/__init__.py
pandas_mate/pkg/prettytable/_compact.py
pandas_mate/pkg/prettytable/cli.py
pandas_mate/pkg/prettytable/factory.py
pandas_mate/pkg/prettytable/prettytable.py
pandas_mate/pkg/rolex/__init__.py
pandas_mate/pkg/rolex/six.py
pandas_mate/pkg/rolex/template.py
pandas_mate/pkg/rolex/zzz_manual_install.py
pandas_mate/tests/__init__.py